ludo_engine/__init__.py
ludo_engine/core/__init__.py
ludo_engine/core/board.py
ludo_engine/core/game.py
ludo_engine/core/player.py
ludo_engine/core/token.py
ludo_engine/models/__init__.py
ludo_engine/models/constants.py
ludo_engine/models/model.py
ludo_engine/strategies/__init__.py
ludo_engine/strategies/base.py
ludo_engine/strategies/llm_strategy.py
ludo_engine/strategies/strategy.py
ludo_engine/strategies/utils.py
ludo_engine/strategies/aggressive/__init__.py
ludo_engine/strategies/aggressive/killer.py
ludo_engine/strategies/aggressive/optimist.py
ludo_engine/strategies/baseline/__init__.py
ludo_engine/strategies/baseline/random_strategy.py
ludo_engine/strategies/baseline/weighted_random.py
ludo_engine/strategies/defensive/__init__.py
ludo_engine/strategies/defensive/cautious.py
ludo_engine/strategies/defensive/defensive.py
ludo_engine/strategies/hybrid/__init__.py
ludo_engine/strategies/hybrid/balanced.py
ludo_engine/strategies/hybrid/winner.py
ludo_engine/strategies/probabilistic/__init__.py
ludo_engine/strategies/probabilistic/hybrid_prob.py
ludo_engine/strategies/probabilistic/probabilistic.py
ludo_engine/strategies/probabilistic/probabilistic_v2.py
ludo_engine/strategies/probabilistic/probabilistic_v3.py
ludo_engine/strategies/special/__init__.py
ludo_engine/strategies/special/human.py
ludo_engine/strategies/special/llm/__init__.py
ludo_engine/strategies/special/llm/prompt.py
ludo_engine/strategies/special/llm/strategy.py
ludo_interface/__init__.py
ludo_interface/app.py
ludo_interface/board_viz.py
ludo_interface/event_handler.py
ludo_interface/game_manager.py
ludo_interface/ui_builder.py
ludo_interface/utils.py
ludo_king_engine-0.1.3.dist-info/licenses/LICENSE
ludo_king_engine-0.1.3.dist-info/METADATA
ludo_king_engine-0.1.3.dist-info/WHEEL
ludo_king_engine-0.1.3.dist-info/entry_points.txt
ludo_king_engine-0.1.3.dist-info/top_level.txt
ludo_king_engine-0.1.3.dist-info/RECORD
