Metadata-Version: 2.4
Name: ludo-king-engine
Version: 0.1.3
Summary: A pure Python implementation of the Ludo game, built for reinforcement learning and strategy testing. The engine defines deterministic rules, cleanly separates game mechanics from strategies, and requires no external libraries.
Author-email: KameniAlexNea <noreply@github.com>
Project-URL: Homepage, https://github.com/KameniAlexNea/ludo-king-engine
Project-URL: Repository, https://github.com/KameniAlexNea/ludo-king-engine
Project-URL: Issues, https://github.com/KameniAlexNea/ludo-king-engine/issues
Keywords: ludo,game,ai,reinforcement-learning,strategy,board-game
Classifier: Development Status :: 4 - Beta
Classifier: Intended Audience :: Developers
Classifier: Intended Audience :: Science/Research
Classifier: License :: OSI Approved :: MIT License
Classifier: Operating System :: OS Independent
Classifier: Programming Language :: Python :: 3
Classifier: Programming Language :: Python :: 3.8
Classifier: Programming Language :: Python :: 3.9
Classifier: Programming Language :: Python :: 3.10
Classifier: Programming Language :: Python :: 3.11
Classifier: Programming Language :: Python :: 3.12
Classifier: Topic :: Games/Entertainment :: Board Games
Classifier: Topic :: Scientific/Engineering :: Artificial Intelligence
Requires-Python: >=3.8
License-File: LICENSE
Provides-Extra: dev
Requires-Dist: tox; extra == "dev"
Provides-Extra: gradio
Requires-Dist: gradio; extra == "gradio"
Requires-Dist: Pillow; extra == "gradio"
Dynamic: license-file
